{
  "name": "Actor Cast",
  "type": {
    "5.0": "0x0186",
    "5.1_cn": "0x012e",
    "5.11_cn": "0x0185",
    "5.15_cn": "0x032C",
    "5.18_cn": "0x008C",
    "5.2_cn": "0x029D",
    "5.21_cn": "0x0146",
    "5.25_cn": "0x0166",
    "5.3_cn": "0x00A5",
    "5.301_cn": "0x0073",
    "5.31_cn": "0x018D",
    "5.35_cn": "0x019F",
    "5.4_cn": "0x0302",
    "5.41_cn": "0x0317",
    "5.5_cn": "0x01E6"
  },
  "enums": [{
    "name": "ActorCastSkillType",
    "type": "uint8",
    "values": [{
      "key": "Normal",
      "value": 1
    }, {
      "key": "ItemAction",
      "value": 2
    }, {
      "key": "MountSkill",
      "value": 13
    }]
  }],
  "fields": [{
    "offset": 0,
    "name": "Action",
    "type": "uint16",
    "length": 2,
    "enum": "$Action"
  }, {
    "offset": 2,
    "name": "skillType",
    "type": "uint8",
    "length": 1,
    "enum": "ActorCastSkillType"
  }, {
    "offset": 3,
    "name": "unknown",
    "type": "uint8",
    "length": 1
  }, {
    "offset": 4,
    "name": "ItemId",
    "type": "uint32",
    "length": 4,
    "enum": "$Item"
  }, {
    "offset": 8,
    "name": "cast_time",
    "type": "float",
    "length": 4
  }, {
    "offset": 12,
    "name": "target_id",
    "type": "uint32",
    "base": "HEX",
    "length": 4
  }, {
    "offset": 16,
    "name": "rotation",
    "type": "float",
    "length": 4
  }, {
    "offset": 20,
    "name": "unknown_2",
    "type": "uint32",
    "length": 4
  }, {
    "offset": 24,
    "name": "posX",
    "type": "uint16",
    "length": 2
  }, {
    "offset": 26,
    "name": "posY",
    "type": "uint16",
    "length": 2
  }, {
    "offset": 28,
    "name": "posZ",
    "type": "uint16",
    "length": 2
  }, {
    "offset": 30,
    "name": "unknown_3",
    "type": "uint16",
    "length": 2
  }]
}